d_mem.v
module d_mem #( parameter DMEM_SIZE = 32) 
              ( input [31:0] addr_dmem,
                input clk, MemRW,
                input [2:0] ReadCntrl,
                output reg [31:0] DataRead)
;

reg [31:0] Data_mem [DMEM_SIZE-1:0]; // array of DMEM_SIZE registers, each 32 bits/4 bytes wth each byte having a unique address
reg [29:0] word_addr;

initial begin
    Data_mem[2] = 32'hDEAD_BEEF;
    Data_mem[5] = 32'h0000_0000;
    Data_mem[6] = 32'hFFFF_FFFF;
    Data_mem[8] = 32'hCAFE_CAFE;
    Data_mem[12] = 32'h0800_0000;
    Data_mem[21] = 32'h2000_7201;
    Data_mem[29] = 32'h53FB_AC02;
end

always @ (posedge clk) begin
    if (!MemRW) begin // if we have to load data from d_mem
        word_addr = addr_dmem [31:2]; 
        case (ReadCntrl) 
        3'b000 : case (addr_dmem[1:0]) // lb
                    2'b00 : DataRead <= {{24{Data_mem[word_addr][7]}},Data_mem[word_addr][7:0]};
                    2'b01 : DataRead <= {{24{Data_mem[word_addr][15]}},Data_mem[word_addr][15:8]};
                    2'b10 : DataRead <= {{24{Data_mem[word_addr][23]}},Data_mem[word_addr][23:16]};
                    2'b11 : DataRead <= {{24{Data_mem[word_addr][31]}},Data_mem[word_addr][31:24]};
                endcase
        3'b001 : case (addr_dmem[1:0]) // lh
                    2'b00 : DataRead <= {{16{Data_mem[word_addr][15]}},Data_mem[word_addr][15:0]};
                    2'b10 : DataRead <= {{16{Data_mem[word_addr][31]}},Data_mem[word_addr][31:16]};
                endcase
        3'b010 : DataRead <= Data_mem[word_addr]; // lw
        3'b100 : case (addr_dmem[1:0]) // lbu
                    2'b00 : DataRead <= {{24'b0},Data_mem[word_addr][7:0]};
                    2'b01 : DataRead <= {{24'b0},Data_mem[word_addr][15:8]};
                    2'b10 : DataRead <= {{24'b0},Data_mem[word_addr][23:16]};
                    2'b11 : DataRead <= {{24'b0},Data_mem[word_addr][31:24]};
                endcase
        3'b101 : case (addr_dmem[1:0]) // lhu
                    2'b00 : DataRead <= {{16'b0},Data_mem[word_addr][15:0]};
                    2'b10 : DataRead <= {{16'b0},Data_mem[word_addr][31:16]};
                endcase
        default : DataRead <= Data_mem[word_addr];
        endcase
    end
    else begin // if we have to store data into d_mem

    end
end

endmodule

d_mem_tb.v
module d_mem_tb ();

reg [31:0] addr_dmem;
reg clk, MemRW;
reg [2:0] ReadCntrl;
wire [31:0] DataRead;

d_mem #(.DMEM_SIZE(32)) u0 (.addr_dmem(addr_dmem),.clk(clk),.MemRW(MemRW),.ReadCntrl(ReadCntrl),.DataRead(DataRead));

always #10 clk = ~clk;

initial begin
    {addr_dmem, clk, ReadCntrl, MemRW} = 37'b1; #10;
    MemRW = 1'b0;
    #10;
    ReadCntrl = 3'b001;
    addr_dmem = 32'h0000_000A;
    #25;
    $display("time=%0t addr_dmem=0x%h DataRead=0x%h", $time, addr_dmem, DataRead);
    ReadCntrl = 3'b010;
    addr_dmem = 32'h0000_0018;
    #25;
    $display("time=%0t addr_dmem=0x%h DataRead=0x%h", $time, addr_dmem, DataRead);
    ReadCntrl = 3'b000;
    addr_dmem = 32'h0000_0055;
    #25;
    $display("time=%0t addr_dmem=0x%h DataRead=0x%h", $time, addr_dmem, DataRead);
    ReadCntrl = 3'b101;
    addr_dmem = 32'h0000_0076;
    #25;
    $display("time=%0t addr_dmem=0x%h DataRead=0x%h", $time, addr_dmem, DataRead);
    #10 $finish;
end

initial begin
    $dumpfile ("d_mem.vcd");
    $dumpvars (0,d_mem_tb);
end

endmodule

d_mem.vcd
$date
	Sat Oct 03 15:49:47 2026
$end
$version
	Icarus Verilog
$end
$timescale
	1s
$end
$scope module d_mem_tb $end
$var wire 32 ! DataRead [31:0] $end
$var reg 1 " MemRW $end
$var reg 3 # ReadCntrl [2:0] $end
$var reg 32 $ addr_dmem [31:0] $end
$var reg 1 % clk $end
$scope module u0 $end
$var wire 1 " MemRW $end
$var wire 3 & ReadCntrl [2:0] $end
$var wire 32 ' addr_dmem [31:0] $end
$var wire 1 % clk $end
$var reg 32 ( DataRead [31:0] $end
$var reg 30 ) word_addr [29:0] $end
$upscope $end
$upscope $end
$enddefinitions $end
#0
$dumpvars
bx )
bx (
b0 '
b0 &
0%
b0 $
b0 #
1"
bx !
$end
#10
b0 )
0"
1%
#20
b1010 $
b1010 '
b1 #
b1 &
0%
#30
b11111111111111111101111010101101 !
b11111111111111111101111010101101 (
b10 )
1%
#40
0%
#45
b11000 $
b11000 '
b10 #
b10 &
#50
b11111111111111111111111111111111 !
b11111111111111111111111111111111 (
b110 )
1%
#60
0%
#70
b1110010 !
b1110010 (
b10101 )
1%
b1010101 $
b1010101 '
b0 #
b0 &
#80
0%
#90
1%
#95
b1110110 $
b1110110 '
b101 #
b101 &
#100
0%
#110
b101001111111011 !
b101001111111011 (
b11101 )
1%
