prog_cntr.v
module prog_cntr (  input [31:0] current_instr_addr,
                    input clk,
                    output reg [31:0] instr_addr)
;

always @ (posedge clk) begin
    instr_addr <= current_instr_addr + 1;
end

endmodule

prog_cntr_tb.v
module prog_cntr_tb ();

reg [31:0] current_instr_addr;
reg clk;
wire [31:0] instr_addr;
integer i;

prog_cntr u0 (.current_instr_addr(current_instr_addr),.clk(clk),.instr_addr(instr_addr));

always #10 clk = ~clk;

initial begin
    {clk, current_instr_addr} = 0; #9;

    repeat (10) @ (posedge clk) begin     
        #1 $display("time=%0t current_instr_addr=0x%h instr_addr=0x%h", $time, current_instr_addr, instr_addr);
        #19;
        current_instr_addr = instr_addr;
    end
    #10 $finish;
end

initial begin
    $dumpfile ("prog_cntr.vcd");
    $dumpvars (0,prog_cntr_tb);
end

endmodule

prog_cntr.vcd
$date
	Tue Sep 15 16:11:14 2026
$end
$version
	Icarus Verilog
$end
$timescale
	1s
$end
$scope module prog_cntr_tb $end
$var wire 32 ! instr_addr [31:0] $end
$var reg 1 " clk $end
$var reg 32 # current_instr_addr [31:0] $end
$scope module u0 $end
$var wire 1 " clk $end
$var wire 32 $ current_instr_addr [31:0] $end
$var reg 32 % instr_addr [31:0] $end
$upscope $end
$upscope $end
$enddefinitions $end
#0
$dumpvars
bx %
b0 $
b0 #
0"
bx !
$end
#10
b1 !
b1 %
1"
#20
0"
#30
b10 !
b10 %
1"
b1 #
b1 $
#40
0"
#50
b11 !
b11 %
1"
b10 #
b10 $
#60
0"
#70
b100 !
b100 %
1"
b11 #
b11 $
#80
0"
#90
b101 !
b101 %
1"
b100 #
b100 $
#100
0"
#110
b110 !
b110 %
1"
b101 #
b101 $
#120
0"
#130
b111 !
b111 %
1"
b110 #
b110 $
#140
0"
#150
b1000 !
b1000 %
1"
b111 #
b111 $
#160
0"
#170
b1001 !
b1001 %
1"
b1000 #
b1000 $
#180
0"
#190
b1010 !
b1010 %
1"
b1001 #
b1001 $
#200
0"
#210
b1011 !
b1011 %
1"
b1010 #
b1010 $
